demasci/__init__.py
demasci-0.0.1.dist-info/WHEEL
demasci-0.0.1.dist-info/METADATA
demasci-0.0.1.dist-info/RECORD
