Metadata-Version: 2.1
Name: demasci
Version: 0.0.1
Summary: Decision Making Science Tools
Author: James Davis
Author-email: jamesmariodavis@gmail.com
Requires-Python: >=3.9,<3.10
Classifier: Programming Language :: Python :: 3
Classifier: Programming Language :: Python :: 3.9
Requires-Dist: numpy (>=1.21.2,<2.0.0)
Requires-Dist: pandas (>=1.3.2,<2.0.0)
